amino/__init__.py
amino/acm.py
amino/client.py
amino/socket.py
amino/sub_client.py
amino/lib/__init__.py
amino/lib/util/__init__.py
amino/lib/util/device.py
amino/lib/util/exceptions.py
amino/lib/util/headers.py
amino/lib/util/helpers.py
amino/lib/util/objects.py
amino/lib/util/voice_header.py
Dick.py-1.7.dist-info/METADATA
Dick.py-1.7.dist-info/WHEEL
Dick.py-1.7.dist-info/top_level.txt
Dick.py-1.7.dist-info/RECORD
