Metadata-Version: 2.1
Name: Dick.py
Version: 1.7
Summary: A library to create Amino bots.
Home-page: https://github.com/aminobot22/MAmino.py
Author: Slimakoi
Author-email: slimeytoficial@gmail.com
License: MIT
Download-URL: https://github.com/aminobot22/MAmino.py.git
Keywords: aminoapps,Dick,amino,amino-bot,narvii,api,python,python3,python3.x,slimakoi,official
Platform: UNKNOWN
Requires-Dist: setuptools
Requires-Dist: requests
Requires-Dist: six
Requires-Dist: websocket-client (==0.57.0)
Requires-Dist: json-minify
Requires-Dist: secmail
Requires-Dist: bs4
Requires-Dist: names
Requires-Dist: requests-random-user-agent
